scaling_analysis/__init__.py
scaling_analysis/experiment.py
scaling_analysis/pca.py
scaling_analysis/plotting.py
scaling_analysis/predict.py
scaling_analysis/predict_history.py
scaling_analysis/session_permutation.py
scaling_analysis/spatial.py
scaling_analysis/svca.py
scaling_analysis/temporal.py
scaling_analysis/utils.py
scaling_analysis/visual.py
scaling_analysis-0.1.0.dist-info/LICENSE.md
scaling_analysis-0.1.0.dist-info/METADATA
scaling_analysis-0.1.0.dist-info/WHEEL
scaling_analysis-0.1.0.dist-info/top_level.txt
scaling_analysis-0.1.0.dist-info/RECORD
