Metadata-Version: 2.1
Name: scaling_analysis
Version: 0.1.0
Summary: Analysis of the dimensionality of neuronal population dynamics as a function of neuron number
Author-email: Jason Manley <jmanley@rockefeller.edu>
License: GNU GENERAL PUBLIC LICENSE
Project-URL: Homepage, https://github.com/vazirilab/scaling_analysis/tree/main/scaling_analysis
Project-URL: Documentation, https://scaling-analysis.readthedocs.io
Project-URL: Issues, https://github.com/vazirilab/scaling_analysis/issues
Classifier: Programming Language :: Python :: 3
Classifier: License :: OSI Approved :: GNU General Public License v3 (GPLv3)
Requires-Python: >=3.8
License-File: LICENSE.md
Requires-Dist: hdf5storage
Requires-Dist: h5py
Requires-Dist: joblib
Requires-Dist: matplotlib
Requires-Dist: numpy
Requires-Dist: PopulationCoding
Requires-Dist: scikit-learn
Requires-Dist: scipy
Requires-Dist: tqdm
